{
  "ACCURACY": [
    {
      "description": "Shivs deal additional damage.",
      "icon": "accuracy.png",
      "name": "Accuracy"
    }
  ],
  "ADAPTATION": [
    {
      "description": "Whenever you enter Wrath, draw 2 cards.",
      "icon": "rushdown.png",
      "name": "Rushdown"
    }
  ],
  "AFTER_IMAGE": [
    {
      "description": "Whenever you play a card, gain Block.",
      "icon": "afterImage.png",
      "name": "After Image"
    }
  ],
  "AMPLIFY": [
    {
      "description": "Your next Power card is played twice.",
      "icon": "amplify.png",
      "name": "Amplify"
    }
  ],
  "A_THOUSAND_CUTS": [
    {
      "description": "Whenever you play a card, deal damage to ALL enemies.",
      "icon": "thousandCuts.png",
      "name": "Thousand Cuts"
    }
  ],
  "BARRICADE": [
    {
      "description": "Block is not removed at the start of your turn.",
      "icon": "barricade.png",
      "name": "Barricade"
    }
  ],
  "BATTLEHYMN": [
    {
      "description": "At the start of each turn, add a Smite into your hand.",
      "icon": "hymn.png",
      "name": "Battle Hymn"
    }
  ],
  "BERSERK": [
    {
      "description": "At the start of your turn, gain Energy.",
      "icon": "berserk.png",
      "name": "Berserk"
    }
  ],
  "BIASED_COGNITION": [
    {
      "description": "At the start of your turn, lose Focus.",
      "icon": "bias.png",
      "name": "Bias"
    }
  ],
  "BLASPHEMY": [
    {
      "description": "At the start of your next turn, you die.",
      "icon": "end_turn_death.png",
      "name": "Blasphemer"
    }
  ],
  "BLUR": [
    {
      "description": "Block is not removed at the start of your next turn.",
      "icon": "blur.png",
      "name": "Blur"
    }
  ],
  "BRUTALITY": [
    {
      "description": "At the start of your turn, lose 1 HP and draw a card.",
      "icon": "brutality.png",
      "name": "Brutality"
    }
  ],
  "BUFFER": [
    {
      "description": "Prevent the next time you would lose HP.",
      "icon": "buffer.png",
      "name": "Buffer"
    }
  ],
  "BURST": [
    {
      "description": "Your next Skill is played twice.",
      "icon": "burst.png",
      "name": "Burst"
    }
  ],
  "CHOKE": [
    {
      "description": "Whenever you play a card this turn, deal damage.",
      "icon": "choke.png",
      "name": "Choked"
    }
  ],
  "COMBUST": [
    {
      "description": "At the end of your turn, lose HP and deal damage to ALL enemies.",
      "icon": "combust.png",
      "name": "Combust"
    }
  ],
  "CORPSE_EXPLOSION": [
    {
      "description": "On death, deal damage equal to max HP to ALL enemies.",
      "icon": "cExplosion.png",
      "name": "Corpse Explosion"
    }
  ],
  "CORRUPTION": [
    {
      "description": "Skills cost 0. Whenever you play a Skill, Exhaust it.",
      "icon": "corruption.png",
      "name": "Corruption"
    }
  ],
  "CREATIVE_AI": [
    {
      "description": "At the start of your turn, add a random Power card into your hand.",
      "icon": "ai.png",
      "name": "Creative AI"
    }
  ],
  "DARK_EMBRACE": [
    {
      "description": "Whenever a card is Exhausted, draw 1 card.",
      "icon": "darkembrace.png",
      "name": "Dark Embrace"
    }
  ],
  "DEMON_FORM": [
    {
      "description": "At the start of your turn, gain Strength.",
      "icon": "demonForm.png",
      "name": "Demon Form"
    }
  ],
  "DEVAFORM": [
    {
      "description": "At the start of your turn, gain increasing Energy.",
      "icon": "deva.png",
      "name": "Deva"
    }
  ],
  "DEVOTION": [
    {
      "description": "At the start of your turn, gain Mantra.",
      "icon": "devotion.png",
      "name": "Devotion"
    }
  ],
  "DOUBLE_TAP": [
    {
      "description": "Your next Attack is played twice.",
      "icon": "doubleTap.png",
      "name": "Double Tap"
    }
  ],
  "ECHO_FORM": [
    {
      "description": "The first card you play each turn is played twice.",
      "icon": "echo.png",
      "name": "Echo Form"
    }
  ],
  "ELECTRODYNAMICS": [
    {
      "description": "Lightning hits ALL enemies.",
      "icon": "infinitegreen.png",
      "name": "Electrodynamics"
    }
  ],
  "ENVENOM": [
    {
      "description": "Whenever you deal unblocked attack damage, apply Poison.",
      "icon": "envenom.png",
      "name": "Envenom"
    }
  ],
  "ESTABLISHMENT": [
    {
      "description": "Whenever a card is Retained, reduce its cost by 1.",
      "icon": "establishment.png",
      "name": "Establishment"
    }
  ],
  "EVOLVE": [
    {
      "description": "Whenever you draw a Status card, draw a card.",
      "icon": "evolve.png",
      "name": "Evolve"
    }
  ],
  "FASTING2": [
    {
      "description": "Gain 1 less Energy each turn.",
      "icon": "fasting.png",
      "name": "Energy Down"
    }
  ],
  "FEEL_NO_PAIN": [
    {
      "description": "Whenever a card is Exhausted, gain Block.",
      "icon": "noPain.png",
      "name": "Feel No Pain"
    }
  ],
  "FIRE_BREATHING": [
    {
      "description": "Whenever you draw a Status or Curse card, deal damage to ALL enemies.",
      "icon": "firebreathing.png",
      "name": "Fire Breathing"
    }
  ],
  "FLAME_BARRIER": [
    {
      "description": "When attacked, deal damage back.",
      "icon": "flameBarrier.png",
      "name": "Flame Barrier"
    }
  ],
  "HEATSINKS": [
    {
      "description": "Whenever you play a Power card, draw a card.",
      "icon": "heatsink.png",
      "name": "Heatsink"
    }
  ],
  "HELLO_WORLD": [
    {
      "description": "At the start of your turn, add a random Common card into your hand.",
      "icon": "hello.png",
      "name": "Hello World"
    }
  ],
  "INFINITE_BLADES": [
    {
      "description": "At the start of your turn, add a Shiv into your hand.",
      "icon": "infiniteBlades.png",
      "name": "Infinite Blades"
    }
  ],
  "JUGGERNAUT": [
    {
      "description": "Whenever you gain Block, deal damage to a random enemy.",
      "icon": "juggernaut.png",
      "name": "Juggernaut"
    }
  ],
  "LIKEWATER": [
    {
      "description": "At the end of your turn, if you are in Calm, gain Block.",
      "icon": "like_water.png",
      "name": "Like Water"
    }
  ],
  "LOCKON": [
    {
      "description": "Orbs deal 50% more damage to this enemy.",
      "icon": "lockon.png",
      "name": "Lock-On"
    }
  ],
  "LOOP": [
    {
      "description": "At the start of your turn, trigger the passive ability of your next Orb.",
      "icon": "loop.png",
      "name": "Loop"
    }
  ],
  "MAGNETISM": [
    {
      "description": "At the start of your turn, add a random Colorless card into your hand.",
      "icon": "magnet.png",
      "name": "Magnetism"
    }
  ],
  "MASTERREALITY": [
    {
      "description": "Whenever a card is created, Upgrade it.",
      "icon": "master_reality.png",
      "name": "Master Reality"
    }
  ],
  "MAYHEM": [
    {
      "description": "At the start of your turn, play the top card of your draw pile.",
      "icon": "mayhem.png",
      "name": "Mayhem"
    }
  ],
  "MENTALFORTRESS": [
    {
      "description": "Whenever you change Stance, gain Block.",
      "icon": "mental_fortress.png",
      "name": "Mental Fortress"
    }
  ],
  "METALLICIZE": [
    {
      "description": "At the end of your turn, gain Block.",
      "icon": "platedarmor.png",
      "name": "Metallicize"
    }
  ],
  "NIRVANA": [
    {
      "description": "Whenever you Scry, gain Block.",
      "icon": "nirvana.png",
      "name": "Nirvana"
    }
  ],
  "NOXIOUS_FUMES": [
    {
      "description": "At the start of your turn, apply Poison to ALL enemies.",
      "icon": "fumes.png",
      "name": "Noxious Fumes"
    }
  ],
  "PANACHE": [
    {
      "description": "Every 5 cards played, deal damage to ALL enemies.",
      "icon": "panache.png",
      "name": "Panache"
    }
  ],
  "PANICBUTTON": [
    {
      "description": "You cannot gain Block from cards.",
      "icon": "noBlock.png",
      "name": "No Block"
    }
  ],
  "PHANTASMAL_KILLER": [
    {
      "description": "Deal Double Damage next turn.",
      "icon": "phantasmal.png",
      "name": "Phantasmal"
    }
  ],
  "RAGE": [
    {
      "description": "Whenever you play an Attack this turn, gain Block.",
      "icon": "anger.png",
      "name": "Rage"
    }
  ],
  "REBOUND": [
    {
      "description": "The next card you play is placed on top of your draw pile.",
      "icon": "rebound.png",
      "name": "Rebound"
    }
  ],
  "RUPTURE": [
    {
      "description": "Whenever you lose HP from a card, gain Strength.",
      "icon": "rupture.png",
      "name": "Rupture"
    }
  ],
  "SADISTIC_NATURE": [
    {
      "description": "Whenever you apply a debuff, deal damage.",
      "icon": "sadistic.png",
      "name": "Sadistic Nature"
    }
  ],
  "SELF_REPAIR": [
    {
      "description": "At the end of combat, heal HP.",
      "icon": "repair.png",
      "name": "Self Repair"
    }
  ],
  "STATIC_DISCHARGE": [
    {
      "description": "Whenever you receive attack damage, Channel Lightning.",
      "icon": "static_discharge.png",
      "name": "Static Discharge"
    }
  ],
  "STORM": [
    {
      "description": "Whenever you play a Power card, Channel Lightning.",
      "icon": "storm.png",
      "name": "Storm"
    }
  ],
  "STUDY": [
    {
      "description": "At the end of your turn, shuffle an Insight into your draw pile.",
      "icon": "book.png",
      "name": "Study"
    }
  ],
  "TALKTOTHEHAND": [
    {
      "description": "Whenever you attack this enemy, gain Block.",
      "icon": "talk_to_hand.png",
      "name": "Block Return"
    }
  ],
  "THE_BOMB": [
    {
      "description": "At the end of 3 turns, deal massive damage to ALL enemies.",
      "icon": "the_bomb.png",
      "name": "The Bomb"
    }
  ],
  "TOOLS_OF_THE_TRADE": [
    {
      "description": "At the start of your turn, draw 1 card and discard 1 card.",
      "icon": "tools.png",
      "name": "Tools of the Trade"
    }
  ],
  "UNDO": [
    {
      "description": "Retain your hand this turn.",
      "icon": "retain.png",
      "name": "Equilibrium"
    }
  ],
  "VENGEANCE": [
    {
      "description": "At the start of your next turn, enter Wrath.",
      "icon": "anger.png",
      "name": "Wrath Next Turn"
    }
  ],
  "WAVEOFTHEHAND": [
    {
      "description": "Whenever you gain Block this turn, apply Weak to ALL enemies.",
      "icon": "wave_of_the_hand.png",
      "name": "Wave of the Hand"
    }
  ],
  "WIREHEADING": [
    {
      "description": "At the start of your turn, Scry.",
      "icon": "wireheading.png",
      "name": "Foresight"
    }
  ],
  "WRAITH_FORM_V2": [
    {
      "description": "At the end of your turn, lose Dexterity.",
      "icon": "wraithForm.png",
      "name": "Wraith Form"
    }
  ]
}