[
  {
    "id": "ACCURSED_BLACKSMITH",
    "name": "Ominous Forge",
    "act": "shrines",
    "description": "You duck into a small hut. Inside, you find what appears to be a forge. The smithing tools are covered with dust, yet a fire roars inside the furnace. You feel on edge...",
    "choices": [
      {
        "option": "[Forge] Upgrade a card in your deck.",
        "description": "",
        "outcome": ""
      },
      {
        "option": "[Rummage] Obtain a special Relic. Become Cursed - Pain.",
        "description": "",
        "outcome": ""
      },
      {
        "option": "[Leave]",
        "description": "",
        "outcome": ""
      },
      {
        "option": "Choose a Card to Upgrade",
        "description": "",
        "outcome": ""
      },
      {
        "option": "[Locked] Requires: Upgradeable Cards",
        "description": "",
        "outcome": ""
      }
    ],
    "image_url": null
  },
  {
    "id": "ADDICT",
    "name": "Pleading Vagrant",
    "act": "city",
    "description": "While sneaking past a group of shrouded figures, one of them approaches you.\n\"Got anything for me friend? Please... maybe some Coin?\"\n\"I just need somewhere to stay, I have treasures I can trade...\"\nHe seems delusional, but harmless.",
    "choices": [
      {
        "option": "[Offer Gold]",
        "description": "",
        "outcome": ""
      },
      {
        "option": "Gold: Obtain a Relic.",
        "description": "",
        "outcome": ""
      },
      {
        "option": "[Locked] Requires:",
        "description": "",
        "outcome": ""
      },
      {
        "option": "Gold.",
        "description": "",
        "outcome": ""
      },
      {
        "option": "[Rob] Obtain a Relic. Become Cursed - Shame.",
        "description": "",
        "outcome": ""
      },
      {
        "option": "[Leave]",
        "description": "",
        "outcome": ""
      }
    ],
    "image_url": null
  },
  {
    "id": "BACK_TO_BASICS",
    "name": "Ancient Writing",
    "act": "city",
    "description": "Scaling the city, you notice a wall covered in the writing of ~Ancients.~ As you try to wrap your head around what the puzzling symbols and glyphs could mean, the writing begins to ~glow.~\nSuddenly, the message becomes clear...",
    "choices": [
      {
        "option": "[Elegance] Remove a card from your deck.",
        "description": "",
        "outcome": ""
      },
      {
        "option": "[Simplicity] Upgrade all Strikes and Defends.",
        "description": "",
        "outcome": ""
      },
      {
        "option": "Select a Card to Remove.",
        "description": "",
        "outcome": ""
      },
      {
        "option": "[Leave]",
        "description": "",
        "outcome": ""
      }
    ],
    "image_url": null
  },
  {
    "id": "BEGGAR",
    "name": "Old Beggar",
    "act": "city",
    "description": "An old beggar cloaked in fur reaches his hands out towards you as you pass. \"Spare some coin, child?\"",
    "choices": [
      {
        "option": "[Offer Gold]",
        "description": "",
        "outcome": ""
      },
      {
        "option": "Gold: Remove a card from your deck.",
        "description": "",
        "outcome": ""
      },
      {
        "option": "[Locked] Requires:",
        "description": "",
        "outcome": ""
      },
      {
        "option": "Gold.",
        "description": "",
        "outcome": ""
      },
      {
        "option": "[Continue]",
        "description": "",
        "outcome": ""
      },
      {
        "option": "[Leave]",
        "description": "",
        "outcome": ""
      },
      {
        "option": "Select a Card to Remove.",
        "description": "",
        "outcome": ""
      }
    ],
    "image_url": null
  },
  {
    "id": "BIG_FISH",
    "name": "Big Fish",
    "act": "exordium",
    "description": "As you make your way down a long corridor you see a banana, a donut, and a box ~floating~ about. No... upon closer inspection they are tied to strings coming from holes in the ceiling. There is a quiet @cackling@ from above as you approach the objects.\nWhat do you do?",
    "choices": [
      {
        "option": "[Banana] Heal",
        "description": "",
        "outcome": ""
      },
      {
        "option": "HP.",
        "description": "",
        "outcome": ""
      },
      {
        "option": "[Donut] Max HP +",
        "description": "",
        "outcome": ""
      },
      {
        "option": ".",
        "description": "",
        "outcome": ""
      },
      {
        "option": "[Box] Obtain a Relic. Become Cursed - Regret.",
        "description": "",
        "outcome": ""
      },
      {
        "option": "[Leave]",
        "description": "",
        "outcome": ""
      }
    ],
    "image_url": null
  },
  {
    "id": "BONFIRE_ELEMENTALS",
    "name": "Bonfire Spirits",
    "act": "shrines",
    "description": "You happen upon a group of what looks like purple fire spirits ~dancing~ around a large bonfire.",
    "choices": [
      {
        "option": "[Continue]",
        "description": "",
        "outcome": ""
      },
      {
        "option": "[Leave]",
        "description": "",
        "outcome": ""
      },
      {
        "option": "[Offer] Receive a reward based on the offer.",
        "description": "",
        "outcome": ""
      },
      {
        "option": "Select a Card to Offer.",
        "description": "",
        "outcome": ""
      }
    ],
    "image_url": null
  },
  {
    "id": "COLOSSEUM",
    "name": "The Colosseum",
    "act": "city",
    "description": "@Thwack!!!@\n..\n......\n...\n~You~ ~were~ ~knocked~ ~unconscious...~",
    "choices": [
      {
        "option": "[Continue]",
        "description": "",
        "outcome": ""
      },
      {
        "option": "[Fight]",
        "description": "",
        "outcome": ""
      },
      {
        "option": "[COWARDICE] Escape.",
        "description": "",
        "outcome": ""
      },
      {
        "option": "[VICTORY] A powerful fight with many rewards.",
        "description": "",
        "outcome": ""
      }
    ],
    "image_url": null
  },
  {
    "id": "CURSED_TOME",
    "name": "Cursed Tome",
    "act": "city",
    "description": "In an abandoned temple, you find a giant book, open, riddled with @cryptic@ @writings.@\n\nAs you try to interpret the elaborate script, it begins to ~shift~ and ~morph~ into writing you are familiar with.",
    "choices": [
      {
        "option": "[Read]",
        "description": "",
        "outcome": ""
      },
      {
        "option": "[Continue] Lose 1 HP.",
        "description": "",
        "outcome": ""
      },
      {
        "option": "[Continue] Lose 2 HP.",
        "description": "",
        "outcome": ""
      },
      {
        "option": "[Continue] Lose 3 HP.",
        "description": "",
        "outcome": ""
      },
      {
        "option": "[Stop] Lose 3 HP.",
        "description": "",
        "outcome": ""
      },
      {
        "option": "[Take] Obtain the Book. Lose",
        "description": "",
        "outcome": ""
      },
      {
        "option": "HP.",
        "description": "",
        "outcome": ""
      },
      {
        "option": "[Leave]",
        "description": "",
        "outcome": ""
      }
    ],
    "image_url": null
  },
  {
    "id": "DEAD_ADVENTURER",
    "name": "Dead Adventurer",
    "act": "exordium",
    "description": "While searching the adventurer you are caught off guard!",
    "choices": [
      {
        "option": "[Search] Find Loot.",
        "description": "",
        "outcome": ""
      },
      {
        "option": "[Leave]",
        "description": "",
        "outcome": ""
      },
      {
        "option": "[Fight]",
        "description": "",
        "outcome": ""
      },
      {
        "option": "[Continue] Find Loot.",
        "description": "",
        "outcome": ""
      },
      {
        "option": "%: monster returns.",
        "description": "",
        "outcome": ""
      }
    ],
    "image_url": null
  },
  {
    "id": "DESIGNER",
    "name": "Designer In-Spire",
    "act": "shrines",
    "description": "You discover a ~colorful~ shop with the banner \"IN-SPIRE\" and walk in to see what's inside.\n\"No, no way. Nope. Can't let you in!\"\n\nA man with ridiculous clothing appears at the entrance to bar you.",
    "choices": [
      {
        "option": "[Continue]",
        "description": "",
        "outcome": ""
      },
      {
        "option": "[Adjustments] Lose",
        "description": "",
        "outcome": ""
      },
      {
        "option": "[Clean Up] Lose",
        "description": "",
        "outcome": ""
      },
      {
        "option": "[Full Service] Lose",
        "description": "",
        "outcome": ""
      },
      {
        "option": "[Punch] Lose",
        "description": "",
        "outcome": ""
      },
      {
        "option": "HP.",
        "description": "",
        "outcome": ""
      },
      {
        "option": "Gold.",
        "description": "",
        "outcome": ""
      },
      {
        "option": "Upgrade",
        "description": "",
        "outcome": ""
      },
      {
        "option": "random cards.",
        "description": "",
        "outcome": ""
      },
      {
        "option": "Upgrade a card.",
        "description": "",
        "outcome": ""
      },
      {
        "option": "Remove a card.",
        "description": "",
        "outcome": ""
      },
      {
        "option": "Transform",
        "description": "",
        "outcome": ""
      },
      {
        "option": "cards.",
        "description": "",
        "outcome": ""
      },
      {
        "option": "Remove a card and upgrade a random card.",
        "description": "",
        "outcome": ""
      },
      {
        "option": "[Leave]",
        "description": "",
        "outcome": ""
      },
      {
        "option": "Choose a Card to Upgrade",
        "description": "",
        "outcome": ""
      },
      {
        "option": "Choose 2 Cards to Transform",
        "description": "",
        "outcome": ""
      },
      {
        "option": "Choose a Card to Remove",
        "description": "",
        "outcome": ""
      }
    ],
    "image_url": null
  },
  {
    "id": "DRUG_DEALER",
    "name": "Augmenter",
    "act": "city",
    "description": "A man with an eyepatch and a devilish grin strides up to you.\n\"Hey there, stranger. Interested in advancing science? I can make you stronger than any training or blessing. You're gonna need it if you're one of those heroes with a death wish.\"\n\n~\"Whad'ya~ ~say?\"~",
    "choices": [
      {
        "option": "[Test J.A.X.] Get JAXXED.",
        "description": "",
        "outcome": ""
      },
      {
        "option": "[Become Test Subject] Transform 2 cards.",
        "description": "",
        "outcome": ""
      },
      {
        "option": "[Ingest Mutagens] Obtain a special relic.",
        "description": "",
        "outcome": ""
      },
      {
        "option": "[Leave]",
        "description": "",
        "outcome": ""
      },
      {
        "option": "[Locked] Requires: 2 or more cards in deck.",
        "description": "",
        "outcome": ""
      },
      {
        "option": "Select Cards to Transform.",
        "description": "",
        "outcome": ""
      }
    ],
    "image_url": null
  },
  {
    "id": "DUPLICATOR",
    "name": "Duplicator",
    "act": "shrines",
    "description": "Before you lies a decorated altar to some ancient entity.",
    "choices": [
      {
        "option": "[Pray] Duplicate a card in your deck.",
        "description": "",
        "outcome": ""
      },
      {
        "option": "[Leave]",
        "description": "",
        "outcome": ""
      },
      {
        "option": "Select a Card to Duplicate.",
        "description": "",
        "outcome": ""
      }
    ],
    "image_url": null
  },
  {
    "id": "FACETRADER",
    "name": "Face Trader",
    "act": "shrines",
    "description": "You walk by an eerie statue holding several masks...\nSomething behind you softly whispers,\n~\"Stop.\"~",
    "choices": [
      {
        "option": "[Touch] Lose",
        "description": "",
        "outcome": ""
      },
      {
        "option": "Gold.",
        "description": "",
        "outcome": ""
      },
      {
        "option": "[Trade] 50%: Good Face. 50%: Bad Face.",
        "description": "",
        "outcome": ""
      },
      {
        "option": "[Leave]",
        "description": "",
        "outcome": ""
      },
      {
        "option": "[Continue]",
        "description": "",
        "outcome": ""
      },
      {
        "option": "HP, gain",
        "description": "",
        "outcome": ""
      }
    ],
    "image_url": null
  },
  {
    "id": "FALLING",
    "name": "Falling",
    "act": "beyond",
    "description": "As you head upwards hopping from one floating shape to another, you slip.\n\nYou begin to fall.",
    "choices": [
      {
        "option": "[Continue]",
        "description": "",
        "outcome": ""
      },
      {
        "option": "[Land] Lose",
        "description": "",
        "outcome": ""
      },
      {
        "option": "[Locked] Requires: Skill Card",
        "description": "",
        "outcome": ""
      },
      {
        "option": "[Channel] Lose",
        "description": "",
        "outcome": ""
      },
      {
        "option": "[Locked] Requires: Power Card",
        "description": "",
        "outcome": ""
      },
      {
        "option": "[Strike] Lose",
        "description": "",
        "outcome": ""
      },
      {
        "option": "[Locked] Requires: Attack Card",
        "description": "",
        "outcome": ""
      },
      {
        "option": "[Leave]",
        "description": "",
        "outcome": ""
      },
      {
        "option": "[Land]",
        "description": "",
        "outcome": ""
      }
    ],
    "image_url": null
  },
  {
    "id": "FORGOTTEN_ALTAR",
    "name": "Forgotten Altar",
    "act": "city",
    "description": "In front of you sits an altar to a forgotten god.\nAtop the altar sits an ornate female statue with arms outstretched.\nShe calls out to you, demanding sacrifice.",
    "choices": [
      {
        "option": "[Offer: Golden Idol] Obtain a special Relic. Lose Golden Idol.",
        "description": "",
        "outcome": ""
      },
      {
        "option": "[Locked] Requires: Golden Idol.",
        "description": "",
        "outcome": ""
      },
      {
        "option": "[Sacrifice] Gain",
        "description": "",
        "outcome": ""
      },
      {
        "option": "Max HP. Lose",
        "description": "",
        "outcome": ""
      },
      {
        "option": "HP.",
        "description": "",
        "outcome": ""
      },
      {
        "option": "[Locked] Requires: Humanity.",
        "description": "",
        "outcome": ""
      },
      {
        "option": "[Desecrate] Become Cursed - Decay.",
        "description": "",
        "outcome": ""
      }
    ],
    "image_url": null
  },
  {
    "id": "FOUNTAIN_OF_CLEANSING",
    "name": "The Divine Fountain",
    "act": "shrines",
    "description": "You come across ~shimmering~ ~water~ flowing endlessly from a fountain on a nearby wall.",
    "choices": [
      {
        "option": "[Drink] Remove all Curses from your deck.",
        "description": "",
        "outcome": ""
      },
      {
        "option": "[Leave]",
        "description": "",
        "outcome": ""
      }
    ],
    "image_url": null
  },
  {
    "id": "GHOSTS",
    "name": "Council of Ghosts",
    "act": "city",
    "description": "As you continue your ascent, ~thick~ ~black~ ~smoke~ begins to billow out of the ground and walls around you, coalescing into three masked forms that start to speak.\n\n~\"Another~ ~puppet~ ~of~ ~Neow~ ~I~ ~think.\"~\n@\"AGREED!@ @SHE@ @ALWAYS@ @MAKES@ @THE@ @FUNNEST@ @TOYS!\"@\n\nYou notice an over-sized grin as the third addresses you.\n\"Ignore the others... Would you like a taste of our ~power?\"~",
    "choices": [
      {
        "option": "[Accept] Receive 5 Apparition. Lose",
        "description": "",
        "outcome": ""
      },
      {
        "option": "Max HP.",
        "description": "",
        "outcome": ""
      },
      {
        "option": "[Refuse]",
        "description": "",
        "outcome": ""
      },
      {
        "option": "[Accept] Receive 3 Apparition. Lose",
        "description": "",
        "outcome": ""
      },
      {
        "option": "[Leave]",
        "description": "",
        "outcome": ""
      }
    ],
    "image_url": null
  },
  {
    "id": "GOLDEN_IDOL",
    "name": "Golden Idol",
    "act": "exordium",
    "description": "You come across an inconspicuous pedestal with a shining gold idol sitting peacefully atop. It looks incredibly valuable.\n\nYou sure don't see any traps nearby.",
    "choices": [
      {
        "option": "[Take] Obtain Golden Idol. Trigger a trap.",
        "description": "",
        "outcome": ""
      },
      {
        "option": "[Leave]",
        "description": "",
        "outcome": ""
      },
      {
        "option": "[Outrun] Become Cursed - Injury.",
        "description": "",
        "outcome": ""
      },
      {
        "option": "[Smash] Take",
        "description": "",
        "outcome": ""
      },
      {
        "option": "Damage.",
        "description": "",
        "outcome": ""
      },
      {
        "option": "[Hide] Lose",
        "description": "",
        "outcome": ""
      },
      {
        "option": "Max HP.",
        "description": "",
        "outcome": ""
      }
    ],
    "image_url": null
  },
  {
    "id": "GOLDEN_SHRINE",
    "name": "Golden Shrine",
    "act": "shrines",
    "description": "Before you lies an elaborate shrine to an ancient spirit.",
    "choices": [
      {
        "option": "[Pray] Gain",
        "description": "",
        "outcome": ""
      },
      {
        "option": "Gold.",
        "description": "",
        "outcome": ""
      },
      {
        "option": "[Desecrate] Gain 275 Gold. Become Cursed - Regret.",
        "description": "",
        "outcome": ""
      },
      {
        "option": "[Leave]",
        "description": "",
        "outcome": ""
      }
    ],
    "image_url": null
  },
  {
    "id": "GOLDEN_WING",
    "name": "Wing Statue",
    "act": "exordium",
    "description": "Among the stone and boulders, you notice an intricate large blue statue resembling a wing.\nYou find gold spilling from its cracks. Maybe there is more inside...",
    "choices": [
      {
        "option": "[Pray] Remove a card from your deck. Lose",
        "description": "",
        "outcome": ""
      },
      {
        "option": "HP.",
        "description": "",
        "outcome": ""
      },
      {
        "option": "[Destroy] Gain",
        "description": "",
        "outcome": ""
      },
      {
        "option": "-",
        "description": "",
        "outcome": ""
      },
      {
        "option": "Gold.",
        "description": "",
        "outcome": ""
      },
      {
        "option": "[Locked] Requires: Card with",
        "description": "",
        "outcome": ""
      },
      {
        "option": "or more damage.",
        "description": "",
        "outcome": ""
      },
      {
        "option": "[Leave]",
        "description": "",
        "outcome": ""
      },
      {
        "option": "[Continue]",
        "description": "",
        "outcome": ""
      },
      {
        "option": "Select a Card to Remove.",
        "description": "",
        "outcome": ""
      }
    ],
    "image_url": null
  },
  {
    "id": "KNOWING_SKULL",
    "name": "Knowing Skull",
    "act": "city",
    "description": "You find yourself in an old, decorated chamber. In the center of the room, a large skull sits atop an ornate pedestal. As you approach, the skull @bursts@ @into@ @flames@ and turns to face you.",
    "choices": [
      {
        "option": "[Continue]",
        "description": "",
        "outcome": ""
      },
      {
        "option": "HP.",
        "description": "",
        "outcome": ""
      },
      {
        "option": "[Information?] Reveal the Boss. Lose",
        "description": "",
        "outcome": ""
      },
      {
        "option": "[Success?] Get a Colorless Card. Lose",
        "description": "",
        "outcome": ""
      },
      {
        "option": "[A Pick Me Up?] Get a Potion. Lose",
        "description": "",
        "outcome": ""
      },
      {
        "option": "[Riches?] Gain",
        "description": "",
        "outcome": ""
      },
      {
        "option": "Gold. Lose",
        "description": "",
        "outcome": ""
      },
      {
        "option": "[How do I leave?] Lose",
        "description": "",
        "outcome": ""
      },
      {
        "option": "[Leave]",
        "description": "",
        "outcome": ""
      }
    ],
    "image_url": null
  },
  {
    "id": "LAB",
    "name": "Lab",
    "act": "shrines",
    "description": "You find yourself in a room filled with racks of test tubes, beakers, flasks, forceps, pinch clamps, stirring rods, tongs, goggles, funnels, pipets, cylinders, condensers, and even a rare spiral tube of glass.\n\nWhy do you know the name of all these tools? It doesn't matter, you take a look around.",
    "choices": [
      {
        "option": "[Search] Find some Potions!",
        "description": "",
        "outcome": ""
      }
    ],
    "image_url": null
  },
  {
    "id": "LIARS_GAME",
    "name": "The Ssssserpent",
    "act": "exordium",
    "description": "You walk into a room to find a large hole in the ground. As you approach the hole, an enormous serpent creature appears from within.\n\n~\"Ho~ ~hooo!~ ~Hello~ ~hello!~ ~what~ ~have~ ~we~ ~got~ ~here?~ Hello adventurer, I ask a simple question.\nThe most fulfilling of lives is that in which you can ~buy~ ~anything!~\nDo you agree?\"",
    "choices": [
      {
        "option": "[Agree] Gain",
        "description": "",
        "outcome": ""
      },
      {
        "option": "Gold. Become Cursed - Doubt.",
        "description": "",
        "outcome": ""
      },
      {
        "option": "[Disagree]",
        "description": "",
        "outcome": ""
      },
      {
        "option": "[Continue]",
        "description": "",
        "outcome": ""
      },
      {
        "option": "[Leave]",
        "description": "",
        "outcome": ""
      }
    ],
    "image_url": null
  },
  {
    "id": "LIVING_WALL",
    "name": "Living Wall",
    "act": "exordium",
    "description": "As you come to a dead-end and begin to turn around, walls @slam@ @down@ from the ceiling, trapping you!\n\nThree faces materialize from the walls and speak.\n\"Forget what you know, and I'll let you go.\"\n\"I require change to see a new space.\"\n\"If you want to pass me, then you must grow.\"",
    "choices": [
      {
        "option": "[Forget] Remove a card from your deck.",
        "description": "",
        "outcome": ""
      },
      {
        "option": "[Change] Transform a card in your deck.",
        "description": "",
        "outcome": ""
      },
      {
        "option": "[Grow] Upgrade a card in your deck.",
        "description": "",
        "outcome": ""
      },
      {
        "option": "Select a Card to Remove.",
        "description": "",
        "outcome": ""
      },
      {
        "option": "Choose a Card to Transform.",
        "description": "",
        "outcome": ""
      },
      {
        "option": "Choose a Card to Upgrade.",
        "description": "",
        "outcome": ""
      },
      {
        "option": "[Leave]",
        "description": "",
        "outcome": ""
      },
      {
        "option": "[Locked] Requires: Upgradeable Cards",
        "description": "",
        "outcome": ""
      }
    ],
    "image_url": null
  },
  {
    "id": "MASKED_BANDITS",
    "name": "Masked Bandits",
    "act": "city",
    "description": "Hehehe.. Thanks for the gold!\nOh, I love gold. It's so nice.\n~shiny~ ~shiny~ chits they are!",
    "choices": [
      {
        "option": "[Pay] Lose ALL of your Gold.",
        "description": "",
        "outcome": ""
      },
      {
        "option": "[Fight!]",
        "description": "",
        "outcome": ""
      },
      {
        "option": "[Continue]",
        "description": "",
        "outcome": ""
      },
      {
        "option": "[Leave]",
        "description": "",
        "outcome": ""
      }
    ],
    "image_url": null
  },
  {
    "id": "MATCH_AND_KEEP",
    "name": "Match and Keep!",
    "act": "shrines",
    "description": "\" Twelve cards! Match them to keep them! Five tries, no do-overs.\nAre you ready? Let's start!\"",
    "choices": [
      {
        "option": "[Continue]",
        "description": "",
        "outcome": ""
      },
      {
        "option": "[Leave]",
        "description": "",
        "outcome": ""
      },
      {
        "option": "[Play]",
        "description": "",
        "outcome": ""
      },
      {
        "option": "Remaining Attempts:",
        "description": "",
        "outcome": ""
      }
    ],
    "image_url": null
  },
  {
    "id": "MINDBLOOM",
    "name": "Mind Bloom",
    "act": "beyond",
    "description": "While walking and traversing through the chaos of the Spire, your thoughts suddenly begin to feel very... ~real...~\n\nImaginings of monsters and riches begin to manifest themselves into reality.\nThe sensation is quickly fleeting. What do you do?",
    "choices": [
      {
        "option": "[I am War] Fight a Boss from Act 1. Obtain a Rare Relic.",
        "description": "",
        "outcome": ""
      },
      {
        "option": "[I am Rich] Gain 999 Gold. Cursed - 2 Normality.",
        "description": "",
        "outcome": ""
      },
      {
        "option": "[I am Healthy] Heal to full HP. Cursed - Doubt.",
        "description": "",
        "outcome": ""
      },
      {
        "option": "[I am Awake] Upgrade all Cards. You can no longer heal.",
        "description": "",
        "outcome": ""
      },
      {
        "option": "[Leave]",
        "description": "",
        "outcome": ""
      }
    ],
    "image_url": null
  },
  {
    "id": "MUSHROOMS",
    "name": "Mushrooms",
    "act": "exordium",
    "description": "You give in to the unnatural desire to eat. As you consume mushroom after mushroom, you feel yourself entering into a daze and pass out. As you awake, you feel very odd.\nYou Heal 25% of your HP, but you also get infected.",
    "choices": [
      {
        "option": "[Stomp] Anger the Mushrooms.",
        "description": "",
        "outcome": ""
      },
      {
        "option": "[Eat] Heal",
        "description": "",
        "outcome": ""
      },
      {
        "option": "HP. Become Cursed - Parasite.",
        "description": "",
        "outcome": ""
      },
      {
        "option": "[Fight]",
        "description": "",
        "outcome": ""
      },
      {
        "option": "[Leave]",
        "description": "",
        "outcome": ""
      }
    ],
    "image_url": null
  },
  {
    "id": "MYSTERIOUS_SPHERE",
    "name": "Mysterious Sphere",
    "act": "beyond",
    "description": "Jutting from the chaotic terrain around you, a bony sphere surrounds a mysterious glowing object within.\nWhile you are curious what lies inside, you notice some sentries keeping an eye on it.",
    "choices": [
      {
        "option": "[Open Sphere] Fight. Reward: Rare Relic.",
        "description": "",
        "outcome": ""
      },
      {
        "option": "[Leave]",
        "description": "",
        "outcome": ""
      },
      {
        "option": "[Fight]",
        "description": "",
        "outcome": ""
      }
    ],
    "image_url": null
  },
  {
    "id": "NEST",
    "name": "The Nest",
    "act": "city",
    "description": "A long line of ~hooded~ ~figures~ can be seen entering\nan unassuming cathedral.",
    "choices": [
      {
        "option": "[Stay in Line] Obtain Ritual Dagger. Lose",
        "description": "",
        "outcome": ""
      },
      {
        "option": "HP.",
        "description": "",
        "outcome": ""
      },
      {
        "option": "[Smash and Grab] Obtain",
        "description": "",
        "outcome": ""
      },
      {
        "option": "Gold.",
        "description": "",
        "outcome": ""
      },
      {
        "option": "[Leave]",
        "description": "",
        "outcome": ""
      },
      {
        "option": "[Continue]",
        "description": "",
        "outcome": ""
      }
    ],
    "image_url": null
  },
  {
    "id": "NOTEFORYOURSELF",
    "name": "A Note For Yourself",
    "act": "shrines",
    "description": "You spot a loose brick within a pillar that catches your eye.",
    "choices": [
      {
        "option": "[Continue]",
        "description": "",
        "outcome": ""
      },
      {
        "option": "[Take and Give] Receive",
        "description": "",
        "outcome": ""
      },
      {
        "option": "and Store a Card.",
        "description": "",
        "outcome": ""
      },
      {
        "option": "[Ignore]",
        "description": "",
        "outcome": ""
      },
      {
        "option": "[Leave]",
        "description": "",
        "outcome": ""
      }
    ],
    "image_url": null
  },
  {
    "id": "N_LOTH",
    "name": "N'loth",
    "act": "shrines",
    "description": "An odd creature with a hunched back sprouting several tentacles is scrounging through a pile of trash and debris in front of you. As you approach, he shuffles towards you in a non-threatening manner.\n\"N'loth hungry. Feed N'loth.\"",
    "choices": [
      {
        "option": "[Offer:",
        "description": "",
        "outcome": ""
      },
      {
        "option": "] Lose this relic. Obtain a special relic.",
        "description": "",
        "outcome": ""
      },
      {
        "option": "[Leave]",
        "description": "",
        "outcome": ""
      }
    ],
    "image_url": null
  },
  {
    "id": "PURIFIER",
    "name": "Purifier",
    "act": "shrines",
    "description": "Before you lies an elaborate shrine to a forgotten spirit.",
    "choices": [
      {
        "option": "[Pray] Remove a card from your deck.",
        "description": "",
        "outcome": ""
      },
      {
        "option": "[Leave]",
        "description": "",
        "outcome": ""
      },
      {
        "option": "Select a Card to Remove.",
        "description": "",
        "outcome": ""
      }
    ],
    "image_url": null
  },
  {
    "id": "SCRAP_OOZE",
    "name": "Scrap Ooze",
    "act": "exordium",
    "description": "As you walk into the room you hear a ~gurgling~ and the @grinding@ of metals. Before you is a slime-like creature that ate too much scrap for its own good. From the center of the creature you see glints of strange light, perhaps something magical? It looks like you can get some treasure if you just reach inside its... opening. However, the acid and sharp objects may hurt.",
    "choices": [
      {
        "option": "[Reach Inside] Lose",
        "description": "",
        "outcome": ""
      },
      {
        "option": "HP.",
        "description": "",
        "outcome": ""
      },
      {
        "option": "%: Find a Relic.",
        "description": "",
        "outcome": ""
      },
      {
        "option": "[Leave]",
        "description": "",
        "outcome": ""
      },
      {
        "option": "[Deeper] Lose",
        "description": "",
        "outcome": ""
      }
    ],
    "image_url": null
  },
  {
    "id": "SECRETPORTAL",
    "name": "Secret Portal",
    "act": "beyond",
    "description": "Before you is a sight that seems out of place in the alien landscape around you. Strangely placed into one of the living walls of the Beyond is an enclosed stone entrance filled with a ~swirling~ ~magical~ ~portal.~\n\nYou aren't sure where it leads, but maybe it could speed your journey through the Spire.",
    "choices": [
      {
        "option": "[Enter the Portal] IMMEDIATELY travel to the boss.",
        "description": "",
        "outcome": ""
      },
      {
        "option": "[Leave]",
        "description": "",
        "outcome": ""
      }
    ],
    "image_url": null
  },
  {
    "id": "SENSORYSTONE",
    "name": "Sensory Stone",
    "act": "beyond",
    "description": "Navigating through the Beyond, you discover a glowing tesseract @spinning@ and ~shifting~ gently in the air.",
    "choices": [
      {
        "option": "[Recall] Add 1 Colorless card to your deck.",
        "description": "",
        "outcome": ""
      },
      {
        "option": "[Recall] Add 2 Colorless cards to your deck. Lose",
        "description": "",
        "outcome": ""
      },
      {
        "option": "[Recall] Add 3 Colorless cards to your deck. Lose",
        "description": "",
        "outcome": ""
      },
      {
        "option": "HP.",
        "description": "",
        "outcome": ""
      },
      {
        "option": "[Leave]",
        "description": "",
        "outcome": ""
      },
      {
        "option": "[Interact]",
        "description": "",
        "outcome": ""
      }
    ],
    "image_url": null
  },
  {
    "id": "SHINING_LIGHT",
    "name": "Shining Light",
    "act": "exordium",
    "description": "You find a shimmering mass of light encompassing the center of the room.\n\nIts ~warm~ ~glow~ and ~enchanting~ ~patterns~ invite you in.",
    "choices": [
      {
        "option": "[Enter] Upgrade 2 random cards. Lose",
        "description": "",
        "outcome": ""
      },
      {
        "option": "HP.",
        "description": "",
        "outcome": ""
      },
      {
        "option": "[Leave]",
        "description": "",
        "outcome": ""
      },
      {
        "option": "[Locked] Requires: Upgradeable Cards",
        "description": "",
        "outcome": ""
      }
    ],
    "image_url": null
  },
  {
    "id": "SPIRE_HEART",
    "name": "Spire Heart",
    "act": "beyond",
    "description": "@tu-thump@ ... @tu-thump@ ... @tu-thump@ ...\nA deep pulsing dread can be felt throughout the room...\nIs this the ~heart~ of the Spire? The source of this evil?",
    "choices": [
      {
        "option": "[Continue]",
        "description": "",
        "outcome": ""
      },
      {
        "option": "[Attack] ???",
        "description": "",
        "outcome": ""
      },
      {
        "option": "[Sleep]",
        "description": "",
        "outcome": ""
      },
      {
        "option": "[Approach Door]",
        "description": "",
        "outcome": ""
      }
    ],
    "image_url": null
  },
  {
    "id": "THE_CLERIC",
    "name": "The Cleric",
    "act": "exordium",
    "description": "A strange blue humanoid with a golden helm(?) approaches you with a huge smile.\n@\"Hello@ @friend!@ I am Cleric! Are you interested in my services?!\" the creature shouts, loudly.",
    "choices": [
      {
        "option": "[Heal] 35 Gold: Heal",
        "description": "",
        "outcome": ""
      },
      {
        "option": "[Locked] Requires:",
        "description": "",
        "outcome": ""
      },
      {
        "option": "Gold.",
        "description": "",
        "outcome": ""
      },
      {
        "option": "[Purify]",
        "description": "",
        "outcome": ""
      },
      {
        "option": "Gold: Remove a card from your deck.",
        "description": "",
        "outcome": ""
      },
      {
        "option": "[Locked] Requires: 50 Gold.",
        "description": "",
        "outcome": ""
      },
      {
        "option": "[Leave]",
        "description": "",
        "outcome": ""
      },
      {
        "option": "Select a Card to Remove.",
        "description": "",
        "outcome": ""
      },
      {
        "option": "HP.",
        "description": "",
        "outcome": ""
      }
    ],
    "image_url": null
  },
  {
    "id": "THE_JOUST",
    "name": "The Joust",
    "act": "city",
    "description": "As you make your way through the large buildings you come across a long narrow bridge and spot knights on either side, facing one another. You approach...\n@\"Halt!\"@\n\nA knight forcefully gestures you to stop with its giant lance.",
    "choices": [
      {
        "option": "[Continue]",
        "description": "",
        "outcome": ""
      },
      {
        "option": "[Murderer] Bet",
        "description": "",
        "outcome": ""
      },
      {
        "option": "Gold - 70%: win",
        "description": "",
        "outcome": ""
      },
      {
        "option": "Gold.",
        "description": "",
        "outcome": ""
      },
      {
        "option": "[Owner] Bet",
        "description": "",
        "outcome": ""
      },
      {
        "option": "Gold - 30%: win",
        "description": "",
        "outcome": ""
      },
      {
        "option": "[Watch]",
        "description": "",
        "outcome": ""
      },
      {
        "option": "[Leave]",
        "description": "",
        "outcome": ""
      }
    ],
    "image_url": null
  },
  {
    "id": "THE_LIBRARY",
    "name": "The Library",
    "act": "city",
    "description": "You come across an ornate building which appears abandoned.\nA plaque that has been torn free from a wall is on the floor. It reads, \"THE LIBRARY\".\nInside, you find countless rows of scrolls, manuscripts, and books.\nYou pick one and cozy yourself into a chair for some quiet time.",
    "choices": [
      {
        "option": "[Read] Choose 1 of 20 cards to add to your deck.",
        "description": "",
        "outcome": ""
      },
      {
        "option": "[Sleep] Heal",
        "description": "",
        "outcome": ""
      },
      {
        "option": "HP.",
        "description": "",
        "outcome": ""
      },
      {
        "option": "[Leave]",
        "description": "",
        "outcome": ""
      },
      {
        "option": "Add a card to your deck.",
        "description": "",
        "outcome": ""
      }
    ],
    "image_url": null
  },
  {
    "id": "THE_MAUSOLEUM",
    "name": "The Mausoleum",
    "act": "city",
    "description": "Venturing through a series of tombs, you are faced with a large sarcophagus ~studded~ ~with~ ~gems~ in the center of a circular room.\nYou cannot make out the writing on the coffin, however, you do notice ~black~ ~fog~ seeping out from the sides.",
    "choices": [
      {
        "option": "[Open Coffin] Obtain a Relic.",
        "description": "",
        "outcome": ""
      },
      {
        "option": "%: Become Cursed - Writhe.",
        "description": "",
        "outcome": ""
      },
      {
        "option": "[Leave]",
        "description": "",
        "outcome": ""
      }
    ],
    "image_url": null
  },
  {
    "id": "THE_MOAI_HEAD",
    "name": "The Moai Head",
    "act": "beyond",
    "description": "You stumble across something that feels very out of place. Before you, an enormous stony head emerges from a large wall segment that does not shift and change like the rest of this area.\nThe head's mouth is wide open, and it reveals large intimidating teeth stained red with blood. The surface of the statue is riddled with pictographs that seem to indicate people throwing themselves into the mouth of this head and being devoured. Why would anyone do that?",
    "choices": [
      {
        "option": "[Jump Inside] Heal to full HP. Lose",
        "description": "",
        "outcome": ""
      },
      {
        "option": "Max HP.",
        "description": "",
        "outcome": ""
      },
      {
        "option": "[Offer: Golden Idol] Gain 333 Gold. Lose Golden Idol.",
        "description": "",
        "outcome": ""
      },
      {
        "option": "[Locked] Requires: Golden Idol.",
        "description": "",
        "outcome": ""
      },
      {
        "option": "[Leave]",
        "description": "",
        "outcome": ""
      }
    ],
    "image_url": null
  },
  {
    "id": "THE_WOMAN_IN_BLUE",
    "name": "The Woman in Blue",
    "act": "shrines",
    "description": "From the darkness, an arm pulls you into a small shop. As your eyes adjust, you see a pale woman in sharp clothes gesturing towards a wall of potions.\n\"Buy a potion. Now!\" she states.",
    "choices": [
      {
        "option": "[Buy 1 Potion]",
        "description": "",
        "outcome": ""
      },
      {
        "option": "[Buy 2 Potions]",
        "description": "",
        "outcome": ""
      },
      {
        "option": "[Buy 3 Potions]",
        "description": "",
        "outcome": ""
      },
      {
        "option": "Gold.",
        "description": "",
        "outcome": ""
      },
      {
        "option": "[Leave]",
        "description": "",
        "outcome": ""
      },
      {
        "option": "[Leave] Take",
        "description": "",
        "outcome": ""
      },
      {
        "option": "Damage.",
        "description": "",
        "outcome": ""
      }
    ],
    "image_url": null
  },
  {
    "id": "TOMB_OF_LORD_RED_MASK",
    "name": "Tomb of Lord Red Mask",
    "act": "beyond",
    "description": "A highly ornamented tomb can be seen on the other side of a floating path. Upon reaching the tomb, you notice a slot for gold coins with a scratched out inscription above it.",
    "choices": [
      {
        "option": "[Don the Red Mask] Gain 222 Gold.",
        "description": "",
        "outcome": ""
      },
      {
        "option": "[Locked] Requires: Red Mask.",
        "description": "",
        "outcome": ""
      },
      {
        "option": "[Offer:",
        "description": "",
        "outcome": ""
      },
      {
        "option": "Gold] Lose all Gold. Obtain a Relic.",
        "description": "",
        "outcome": ""
      },
      {
        "option": "[Leave]",
        "description": "",
        "outcome": ""
      }
    ],
    "image_url": null
  },
  {
    "id": "TRANSMORGRIFIER",
    "name": "Transmogrifier",
    "act": "shrines",
    "description": "Before you lies an elaborate shrine to a forgotten spirit.",
    "choices": [
      {
        "option": "[Pray] Transform a card.",
        "description": "",
        "outcome": ""
      },
      {
        "option": "[Leave]",
        "description": "",
        "outcome": ""
      },
      {
        "option": "Select a Card to Transform.",
        "description": "",
        "outcome": ""
      }
    ],
    "image_url": null
  },
  {
    "id": "UPGRADE_SHRINE",
    "name": "Upgrade Shrine",
    "act": "shrines",
    "description": "Before you lies an elaborate shrine to a forgotten spirit.",
    "choices": [
      {
        "option": "[Pray] Upgrade a card.",
        "description": "",
        "outcome": ""
      },
      {
        "option": "[Leave]",
        "description": "",
        "outcome": ""
      },
      {
        "option": "Select a Card to Upgrade.",
        "description": "",
        "outcome": ""
      },
      {
        "option": "[Locked] Requires: Upgradeable Cards",
        "description": "",
        "outcome": ""
      }
    ],
    "image_url": null
  },
  {
    "id": "VAMPIRES",
    "name": "Vampires(?)",
    "act": "city",
    "description": "Navigating an unlit street, you come across several hooded figures in the midst of some dark ritual. As you approach, they turn to you in eerie unison. The tallest among them bares fanged teeth and extends a long, pale hand towards you.\n~\"Join~ ~us~ ~brother,~ ~and~ ~feel~ ~the~ ~warmth~ ~of~ ~the~ ~Spire.\"~",
    "choices": [
      {
        "option": "[Accept] Remove all Strikes. Receive 5 Bites. Lose",
        "description": "",
        "outcome": ""
      },
      {
        "option": "Max HP.",
        "description": "",
        "outcome": ""
      },
      {
        "option": "[Refuse]",
        "description": "",
        "outcome": ""
      },
      {
        "option": "[Lose",
        "description": "",
        "outcome": ""
      },
      {
        "option": "] Remove all Strikes. Receive 5 Bites.",
        "description": "",
        "outcome": ""
      },
      {
        "option": "[Leave]",
        "description": "",
        "outcome": ""
      }
    ],
    "image_url": null
  },
  {
    "id": "WEMEETAGAIN",
    "name": "We Meet Again!",
    "act": "shrines",
    "description": "\"We meet again!\"\nA cheery disheveled fellow approaches you gleefully. You do not know this man.\n\n\"It's me, Ranwid! Have any goods for me today? The usual? A fella like me can't make it alone, you know?\"\nYou eye him suspiciously and consider your options...",
    "choices": [
      {
        "option": "[Give Potion] Lose",
        "description": "",
        "outcome": ""
      },
      {
        "option": "[Locked] Requires: Potion.",
        "description": "",
        "outcome": ""
      },
      {
        "option": "[Give Gold] Lose",
        "description": "",
        "outcome": ""
      },
      {
        "option": "[Locked] Requires: At least 50 Gold.",
        "description": "",
        "outcome": ""
      },
      {
        "option": "[Give Card] Lose",
        "description": "",
        "outcome": ""
      },
      {
        "option": "[Locked] Requires: Card.",
        "description": "",
        "outcome": ""
      },
      {
        "option": ". Obtain a Relic.",
        "description": "",
        "outcome": ""
      },
      {
        "option": "[Attack]",
        "description": "",
        "outcome": ""
      },
      {
        "option": "[Leave]",
        "description": "",
        "outcome": ""
      },
      {
        "option": "Gold",
        "description": "",
        "outcome": ""
      }
    ],
    "image_url": null
  },
  {
    "id": "WHEEL_OF_CHANGE",
    "name": "Wheel of Change",
    "act": "shrines",
    "description": "You come upon a dapper looking, cheery gremlin.\n\"It's time to spin the wheel! Are you ~R~ ~E~ ~A~ ~D~ ~Y~ ~?~ Of course you are!\"",
    "choices": [
      {
        "option": "[Play]",
        "description": "",
        "outcome": ""
      },
      {
        "option": "[Prize!] YAY!!!!",
        "description": "",
        "outcome": ""
      },
      {
        "option": "[Prize!] Obtain a Relic.",
        "description": "",
        "outcome": ""
      },
      {
        "option": "[Prize!] Heal to full health.",
        "description": "",
        "outcome": ""
      },
      {
        "option": "[Prize?] Curse - Decay.",
        "description": "",
        "outcome": ""
      },
      {
        "option": "[Prize!] Remove a card from your deck.",
        "description": "",
        "outcome": ""
      },
      {
        "option": "[Prize?] Lose",
        "description": "",
        "outcome": ""
      },
      {
        "option": "HP.",
        "description": "",
        "outcome": ""
      },
      {
        "option": "[Leave]",
        "description": "",
        "outcome": ""
      },
      {
        "option": "Select a Card to Remove.",
        "description": "",
        "outcome": ""
      }
    ],
    "image_url": null
  },
  {
    "id": "WINDING_HALLS",
    "name": "Winding Halls",
    "act": "beyond",
    "description": "As you slowly make your way up the twisting pathways, you constantly find yourself losing your way as the walls and ground seem to inexplicably shift before your eyes.\n\nThe constant ~whispering~ ~voices~ in the back of your head aren't helping things either.",
    "choices": [
      {
        "option": "...",
        "description": "",
        "outcome": ""
      },
      {
        "option": "[Embrace Madness] Receive 2 Madness. Lose",
        "description": "",
        "outcome": ""
      },
      {
        "option": "HP.",
        "description": "",
        "outcome": ""
      },
      {
        "option": "[Focus] Become Cursed - Writhe. Heal",
        "description": "",
        "outcome": ""
      },
      {
        "option": "[Leave]",
        "description": "",
        "outcome": ""
      },
      {
        "option": "HP.",
        "description": "",
        "outcome": ""
      },
      {
        "option": "[Retrace Your Steps] Lose",
        "description": "",
        "outcome": ""
      },
      {
        "option": "Max HP.",
        "description": "",
        "outcome": ""
      }
    ],
    "image_url": null
  },
  {
    "id": "WORLD_OF_GOOP",
    "name": "World of Goop",
    "act": "exordium",
    "description": "You fall into a puddle.\n@IT'S@ @MADE@ @OF@ @SLIME@ @GOOP!!@\nFrantically, you claw yourself out over several minutes as you feel the goop starting to burn.\nYou can feel goop in your ears, goop in your nose, goop everywhere.\n\nClimbing out, you notice that some of your gold is missing. Looking back to the puddle you see your missing coins combined with gold from unfortunate adventurers mixed together in the puddle.",
    "choices": [
      {
        "option": "[Gather Gold] Gain",
        "description": "",
        "outcome": ""
      },
      {
        "option": "Gold. Lose",
        "description": "",
        "outcome": ""
      },
      {
        "option": "HP.",
        "description": "",
        "outcome": ""
      },
      {
        "option": "[Leave It] Lose",
        "description": "",
        "outcome": ""
      },
      {
        "option": "Gold.",
        "description": "",
        "outcome": ""
      },
      {
        "option": "[Leave]",
        "description": "",
        "outcome": ""
      }
    ],
    "image_url": null
  }
]
